viewinline/__init__.py
viewinline/viewinline.py
viewinline-0.1.4.dist-info/METADATA
viewinline-0.1.4.dist-info/WHEEL
viewinline-0.1.4.dist-info/entry_points.txt
viewinline-0.1.4.dist-info/RECORD
