Metadata-Version: 2.4
Name: viewinline
Version: 0.1.4
Summary: Quick look geospatial viewer for iTerm2 and ANSI compatible terminals
Project-URL: Homepage, https://github.com/nkeikon/viewinline
Project-URL: Repository, https://github.com/nkeikon/viewinline
Project-URL: Issues, https://github.com/nkeikon/viewinline/issues
Author: Keiko Nomura
License: MIT
Requires-Python: >=3.9
Requires-Dist: geopandas
Requires-Dist: matplotlib
Requires-Dist: numpy
Requires-Dist: pillow
Requires-Dist: pyogrio
Requires-Dist: rasterio
